Metadata-Version: 2.1
Name: odoo8-addon-account-reconcile-trace
Version: 8.0.1.0.0.99.dev28
Summary: Account Reconcile Trace
Home-page: http://www.domatix.com
Author: Domatix,Odoo Community Association (OCA)
Author-email: support@odoo-community.org
License: AGPL-3
Platform: UNKNOWN
Classifier: Programming Language :: Python
Classifier: Framework :: Odoo
Classifier: Framework :: Odoo :: 8.0
Classifier: License :: OSI Approved :: GNU Affero General Public License v3
Requires-Python: ~=2.7
Requires-Dist: odoo (<9.0a,>=8.0a)
